[{
		"number": "1",
		"word": [""]
	}, {
		"number": "2",
		"word": ["必读","重要","重大","主要","首要","热点","流行","热搜","潮流","热门","最新","最近","要闻","首要","重要","主要","时政","政治","头条","国内","中国","大陆","财经","金融","经济","财政","贸易","财税","理财","投资","基金","期货","国债","储蓄","债券","信托","外汇","保险","珠宝","财富","股票","股市","炒股","证券","H股","娱乐","八卦","明星","艺人","演员","体育","运动","健身","竞技","体操","科技","IT","数码","社会","人文","生活","军事","军队","部队","军人","军务","国防","国际","全球","世界","外国","外交","国外","文化","人文","历史","地理","房产","买房","卖房","租房","物业","房价","房市","汽车","前装","后装","车载","车机","机车","游戏","电竞","篮球","电影","影视","教育","培训","培养","育儿","视频","美剧","韩剧","搏击","搏斗","格斗","拳击","综艺","音乐","歌星","歌曲","专辑","歌词","电台","科普","科学","足球","蹴鞠","时尚","潮流","流行","服装","时髦","美妆","旅游","旅行","观光","出游","传媒","媒体","媒介","韩流","韩国","韩星","韩剧","电竞"]
	}, {
		"number": "3",
		"word": ["最新鲜","创业板","蓝筹股","中小板","娱乐圈","体育界","高科技","计算机","房地产","教育界","电视剧","真人秀","演唱会","时尚圈","时尚界","自驾游","跟团游"]
	}, {
		"number": "4",
		"word": ["应该看的","时下流行","超级话题","刚刚发布","新近发布","至关重要","时事政治","头版头条","国家内部","市场经济","财务管理","股指期货","娱乐明星","体育比赛","体育竞赛","体育活动","体育设施","球类运动","信息科技","电子技术","数码产品","智能硬件","道德伦理","风俗习惯","趣闻轶事","婚姻家庭","奇异现象","官司纠纷","感情纠葛","灾难事故","武装设备","风土人情","传统习俗","生活方式","宗教信仰","文学艺术","思维方式","价值观念","审美情趣","精神图腾","哲学思想","制度文化","篮球联盟","夏季联赛","搞笑节目","谈话节目","饮食节目","游戏节目","选秀节目","音乐节目","文艺晚会","科学技术"]
	}, {
		"number": "5",
		"word": [""]
	}, {
		"number": "6",
		"word": ["信息通信技术","职业篮球联赛","婚姻速配节目"]
	}, {
		"number": "7",
		"word": [""]
	}
]