[
    {
        "id": "TimeConsuming",
        "word": "导航去某地耗时",
        "mainCase": [
            "从[Keyword][TravelMode]去[Keyword]要多久",
			"[TravelMode]从[Keyword]去[Keyword]要多久",
			"查询[TravelMode]从[Keyword]去[Keyword]要多久",
			"从[Keyword]去[Keyword][TravelMode]要多久",
			"查询从[Keyword]去[Keyword][TravelMode]要多久",
			"从[Keyword][TravelMode]去[Keyword]要多长时间",
			"[TravelMode]从[Keyword]去[Keyword]要多长时间",
			"查询[TravelMode]从[Keyword]去[Keyword]要多长时间",
			"从[Keyword]去[Keyword][TravelMode]要多长时间",
			"查询从[Keyword]去[Keyword][TravelMode]要多长时间",
			"从[Keyword][TravelMode]去[Keyword]需要多久",
			"[TravelMode]从[Keyword]去[Keyword]需要多久",
			"查询[TravelMode]从[Keyword]去[Keyword]需要多久",
			"从[Keyword]去[Keyword][TravelMode]需要多久",
			"查询从[Keyword]去[Keyword][TravelMode]需要多久",
			"从[Keyword][TravelMode]去[Keyword]需要多长时间",
			"[TravelMode]从[Keyword]去[Keyword]需要多长时间",
			"查询[TravelMode]从[Keyword]去[Keyword]需要多长时间",
			"从[Keyword]去[Keyword][TravelMode]需要多长时间",
			"查询从[Keyword]去[Keyword][TravelMode]需要多长时间",
			"从[Keyword][TravelMode]去[Keyword]要花多久",
			"[TravelMode]从[Keyword]去[Keyword]要花多久",
			"查询[TravelMode]从[Keyword]去[Keyword]要花多久",
			"从[Keyword]去[Keyword][TravelMode]要花多久",
			"查询从[Keyword]去[Keyword][TravelMode]要花多久",
			"从[Keyword][TravelMode]去[Keyword]要花多长时间",
			"[TravelMode]从[Keyword]去[Keyword]要花多长时间",
			"查询[TravelMode]从[Keyword]去[Keyword]要花多长时间",
			"从[Keyword]去[Keyword][TravelMode]要花多长时间",
			"查询从[Keyword]去[Keyword][TravelMode]要花多长时间"
        ]
    },
    {
        "id": "PredictingTheFuture",
        "word": "预测未来驾车到某地的耗时（非立即出发）",
        "mainCase": [
            "[DateTime]开车去[Keyword]要多久",
			"[DateTime]驾车去[Keyword]要多久",
			"开车[DateTime]去[Keyword]要多久",
			"驾车[DateTime]去[Keyword]要多久",
			"开车去[Keyword][DateTime]要多久",
			"驾车去[Keyword][DateTime]要多久",
			"[DateTime]开车去[Keyword]要花多久",
			"[DateTime]驾车去[Keyword]要花多久",
			"开车[DateTime]去[Keyword]要花多久",
			"驾车[DateTime]去[Keyword]要花多久",
			"开车去[Keyword][DateTime]要花多久",
			"驾车去[Keyword][DateTime]要花多久",
			"[DateTime]开车去[Keyword]需要花多久",
			"[DateTime]驾车去[Keyword]需要花多久",
			"开车[DateTime]去[Keyword]需要花多久",
			"驾车[DateTime]去[Keyword]需要花多久",
			"开车去[Keyword][DateTime]需要花多久",
			"驾车去[Keyword][DateTime]需要花多久",
			"[DateTime]的时候开车去[Keyword]要多久",
			"[DateTime]的时候驾车去[Keyword]要多久",
			"开车[DateTime]的时候去[Keyword]要多久",
			"驾车[DateTime]的时候去[Keyword]要多久",
			"开车去[Keyword][DateTime]的时候要多久",
			"驾车去[Keyword][DateTime]的时候要多久",
			"[DateTime]的时候开车去[Keyword]要花多久",
			"[DateTime]的时候驾车去[Keyword]要花多久",
			"开车[DateTime]的时候去[Keyword]要花多久",
			"驾车[DateTime]的时候去[Keyword]要花多久",
			"开车去[Keyword][DateTime]的时候要花多久",
			"驾车去[Keyword][DateTime]的时候要花多久",
			"[DateTime]的时候开车去[Keyword]需要花多久",
			"[DateTime]的时候驾车去[Keyword]需要花多久",
			"开车[DateTime]的时候去[Keyword]需要花多久",
			"驾车[DateTime]的时候去[Keyword]需要花多久",
			"开车去[Keyword][DateTime]的时候需要花多久",
			"驾车去[Keyword][DateTime]的时候需要花多久"
        ]
    },
    {
        "id": "ForecastCost",
        "word": "预测到某地的费用",
        "mainCase": [
            "从[HomeOrCom][TravelMode]去[Keyword]要多久",
			"[TravelMode]从[HomeOrCom]去[Keyword]要多久",
			"查询[TravelMode]从[HomeOrCom]去[Keyword]要多久",
			"从[HomeOrCom]去[Keyword][TravelMode]要多久",
			"查询从[HomeOrCom]去[Keyword][TravelMode]要多久",
			"从[HomeOrCom][TravelMode]去[Keyword]要多长时间",
			"[TravelMode]从[HomeOrCom]去[Keyword]要多长时间",
			"查询[TravelMode]从[HomeOrCom]去[Keyword]要多长时间",
			"从[HomeOrCom]去[Keyword][TravelMode]要多长时间",
			"查询从[HomeOrCom]去[Keyword][TravelMode]要多长时间",
			"从[HomeOrCom][TravelMode]去[Keyword]需要多久",
			"[TravelMode]从[HomeOrCom]去[Keyword]需要多久",
			"查询[TravelMode]从[HomeOrCom]去[Keyword]需要多久",
			"从[HomeOrCom]去[Keyword][TravelMode]需要多久",
			"查询从[HomeOrCom]去[Keyword][TravelMode]需要多久",
			"从[HomeOrCom][TravelMode]去[Keyword]需要多长时间",
			"[TravelMode]从[HomeOrCom]去[Keyword]需要多长时间",
			"查询[TravelMode]从[HomeOrCom]去[Keyword]需要多长时间",
			"从[HomeOrCom]去[Keyword][TravelMode]需要多长时间",
			"查询从[HomeOrCom]去[Keyword][TravelMode]需要多长时间",
			"从[HomeOrCom][TravelMode]去[Keyword]要花多久",
			"[TravelMode]从[HomeOrCom]去[Keyword]要花多久",
			"查询[TravelMode]从[HomeOrCom]去[Keyword]要花多久",
			"从[HomeOrCom]去[Keyword][TravelMode]要花多久",
			"查询从[HomeOrCom]去[Keyword][TravelMode]要花多久",
			"从[HomeOrCom][TravelMode]去[Keyword]要花多长时间",
			"[TravelMode]从[HomeOrCom]去[Keyword]要花多长时间",
			"查询[TravelMode]从[HomeOrCom]去[Keyword]要花多长时间",
			"从[HomeOrCom]去[Keyword][TravelMode]要花多长时间",
			"查询从[HomeOrCom]去[Keyword][TravelMode]要花多长时间"
        ]
    }
]