[{
	"number": "1",
	"word": ["猪","狗","鸡","猴","羊","马","蛇","龙","兔","牛","鼠"]
},
{
	"number": "2",
	"word": ["亥猪","属猪","戌狗","属狗","酉鸡","属鸡","申猴","属猴","未羊","属羊","午马","属马","巳蛇","小龙","属蛇","辰龙","属龙","卯兔","属兔","寅虎","属虎","丑牛","属牛","子鼠","属鼠"]
},
{
	"number": "3",
	"word": ["猪属相","属相猪","狗属相","属相狗","鸡属相","属相鸡","猴属相","属相猴","羊属相","属相羊","马属相","属相马","蛇属相","属相蛇","龙属相","属相龙","兔属相","属相兔","兔属相","属相兔","属兔的","虎属相","属相虎","牛属相","属相牛","鼠属相","属相鼠","属鼠的","请选择"]
},
{
	"number": "4",
	"word": ["属相小龙","小龙属相","属相小鼠","小鼠属相","属相小牛","小牛属相","属相小兔","小兔属相","属相小蛇","小蛇属相","属相小马","小马属相","属相小羊","小羊属相","属相小猴","小猴属相","属相小鸡","小鸡属相","属相小猪","小龙属猪","属相小狗","小龙属狗"]
},
{
	"number": "5",
	"word": [""]
},
{
	"number": "6",
	"word": [""]
},
{
	"number": "7",
	"word": [""]
}]